callable_module/__init__.py
callable_module-0.0.2.dist-info/METADATA
callable_module-0.0.2.dist-info/WHEEL
callable_module-0.0.2.dist-info/top_level.txt
callable_module-0.0.2.dist-info/RECORD
