Metadata-Version: 2.4
Name: callable-module
Version: 0.0.2
Summary: Make callables into modules
Author-email: Jason Wilkes <notarealdeveloper@gmail.com>
Project-URL: source, https://github.com/notarealdeveloper/callable-module
Project-URL: download, https://pypi.org/project/callable-module/#files
